pypi_test_castellani_davide_01_01/__init__.py
pypi_test_castellani_davide_01_01/test_pypi_test_castellani_davide_01_01.py
pypi_test_castellani_davide_01_01_castellani_davide-1.0.dist-info/METADATA
pypi_test_castellani_davide_01_01_castellani_davide-1.0.dist-info/WHEEL
pypi_test_castellani_davide_01_01_castellani_davide-1.0.dist-info/top_level.txt
pypi_test_castellani_davide_01_01_castellani_davide-1.0.dist-info/zip-safe
pypi_test_castellani_davide_01_01_castellani_davide-1.0.dist-info/RECORD
