Metadata-Version: 2.1
Name: pypi-test-castellani-davide-01-01-castellani-davide
Version: 1.0
Summary: Descrizione
Home-page: https://github.com/CastellaniDavide/pypi_test_castellani_davide_01_01
Author: CastellaniDavide
Author-email: help@castellanidavide.it
License: GNU
Platform: linux_distibution
Requires-Python: >=3.7
